README.md
setup.py
netswitch/__init__.py
netswitch/__main__.py
netswitch/cell.py
netswitch/core.py
netswitch/etciface_gen.py
netswitch/etcinterfaces.py
netswitch/iw.py
netswitch/systemctl_install.py
netswitch/util.py
netswitch/wpasup.py
netswitch.egg-info/PKG-INFO
netswitch.egg-info/SOURCES.txt
netswitch.egg-info/dependency_links.txt
netswitch.egg-info/entry_points.txt
netswitch.egg-info/requires.txt
netswitch.egg-info/top_level.txt