Metadata-Version: 2.1
Name: netswitch
Version: 0.1.1
Summary: wifi switching
Home-page: https://github.com/beasteers/netswitch
Author: Bea Steers
Author-email: bea.steers@gmail.com
License: BSD 3-Clause Clear License
Keywords: wifi switching network raspberry pi wpa supplicant wlan wlan0 ppp0 eth0
Platform: UNKNOWN
